{"Q4ymrVRJM/Lk0znpJxpKUg==":"logo%20tk-141x139.jpg","WfvxffBudBcSmNrYXCC+5Q==":"depan%20tk%20anak2-1900x1425.jpg","ri54i3j5mGRFZR7sMda3bQ==":"untitled%20diagram.drawio-601x311.png","ss3zjL2j9pai3vXr4C8QuQ==":"untitled%20diagram.drawio%20(2)-931x351.png","MTKN2aOiABvBKxiQF3hfPA==":"nurida-530x707.jpeg","X1Vo3jRtukwa/bUnLwzjIg==":"laili-530x707.jpeg","p+a5U86fTDEFWitXC5xebw==":"bu%20eni-561x848.jpg","azG5gvOzFtx3J/iujr46KA==":"bu%20sanggrahan-561x848.jpg","AwoPxSSLzBoStgaPmrfxww==":"bu%20nikmah-561x848.jpg","iTESCZ9U213hXTMXpTMkTA==":"ekstra%20drumband-1280x960.jpg","DGjYq9AenefdFbwIp7JD3w==":"guru2tk2-1280x853.jpg","+GAgkVdk1jtZqvxTgekoTw==":"foto%20ummi-1280x763.jpg","tjHRepSR7olDZvGiGEBH1w==":"foto%20p%20gito%20upload-561x847.jpg","vIuVa2iWGd+sJhwbJoCAEw==":"fb_img-1670382526808-720x534.jpg","0k7MJVMTiQoVZtB5GuyCzg==":"fb_img-1670382957808-960x1280.jpg","xxS5SBauECmOMn+Uw7Hhpw==":"fb_img-1670382962907-1080x810.jpg","7xfQlUYXyP9WypV5cLcfVg==":"fb_img-1670382968156-1080x608.jpg","KfoCp7mdIf3Iub/SWPYcPA==":"fb_img-1670383095928-1080x718.jpg","+x4CNSR3oPkFpt1eAto5zA==":"fb_img-1670383223201-1080x810.jpg","mGdYxwa06eWCk1BWw0EniA==":"fb_img-1670382651870-1080x1080.jpg","Ll7l6FD7WwvnwwBz1us43Q==":"fb_img_1670383186373%20(2)-1080x810.jpg","D6Oyh5KAhlloUSJMGPsF/Q==":"fb_img_1670382946128%20(1)-609x457.jpg","aQmsO3DphYQPTmCdVLzN3Q==":"fb_img_1670383197806%20(1)-1080x810.jpg","zuL21mOZNkCMl1QAPkeRlw==":"fb_img_1670383197806%20(1)-1080x810.jpeg","D5CPFPLV50/SKy5DWuMdzQ==":"fb_img_1670382645235%20(2)-1080x1080.jpg","02vMW7NgfFbpIY8MRqEVIQ==":"fb_img_1670382645235%20(11)-770x770.jpeg","eUp0wEmcf0O4F+Wk2rzkSg==":"fb_img_1670383197806%20(1)-1080x810.jpeg","k6cE4TtFLyYOINiJIsX08w==":"jathilan-607x607.jpg","ceoJ5ZNvq8IQNPJTudJFbw==":"20221214-72114-1076x1913.jpeg","o0As/ritUY4bZlrcwY6OTw==":"20221214-81719-609x1253.jpeg","gdL4FjD3aP+F2lEGohIwQA==":"brosur%20tk-1836x1298.jpg","wOOAahsvOxUoLLW3x5PeEQ==":"sambutan%20tk-1073x1600.jpg","N1wF4lebUKMrW+wIH9AdpQ==":"20221214-72115-1600x2844.jpeg","FF+RglajSD7YrUpD1KeCjA==":"img-20221214-wa0011-5-561x748.jpeg","AyqfrZ7Si7K6twZE6QfqjA==":"img-20221214-wa0011-6-561x748.jpeg","lIN5xFb/WCJiB3xSV+R5kg==":"img-20221215-wa0012.jpeg","bKvzTOerXsuryvxShlBtVw==":"img-20221215-wa0013.jpeg","oZapDwYBxzjEc5dcxDXolQ==":"img-20221215-wa0011.jpeg","+szH+KwKXfRtcik3quPB1w==":"img-20221215-wa0010.jpg","lqAwQukygQzHAo370WLhCw==":"img-20221215-wa0010.jpeg","P66ZttMFjmVI2qNHOtB0SQ==":"fb_img-1670382962907-1080x810.jpeg","0zROFEGKJAtYhf9Thl7vMg==":"screenshot-20221217-141611-vanced.jpeg","MpLC4v7H8MDzQv55xwLOIA==":"screenshot-20221217-141611-vanced-1.jpeg","4TSo+2E1C2o0ErFC/74pKQ==":"fb_img-1670382962908-1080x810.jpeg","6EijRQep8omEhg4kts/Ofw==":"screenshot-20221217-141611-vanced-2.jpeg","Li2rR0+2Ag3xiidHd4J7ig==":"screenshot-20221217-141611-vanced.jpg","mfRvABTPwcHpIo8pV7yCMQ==":"screenshot-20221217-141611-vanced-3.jpeg","JvrymKdLyk4oh74RKwQIsg==":"20221214-80620.jpeg","xChrlUStBkbF+Q24KRHUZg==":"20221214-80621.jpeg","1hbHsQqW2+tl//1EmZwluw==":"20221214-80622.jpeg","AGXlFjWqKXYinB42cIXIgw==":"20221214-75145.jpeg","5sz89AQBPdIG4CcjdtHxxg==":"20221214-75132.jpeg","W3nvAYD/YYhwqYto7jlq6Q==":"20221214-80815.jpeg","XYjXs7sHDbXUtiUr1qW6yg==":"20221214-80949.jpeg","Hc0wN/2BV+J7Cw10XC54cA==":"20221214-80833.jpg","NoTGlxBhf1teVN7kxCHYmg==":"20221214-80833.jpeg","9Cuubd0bS+Va9hnX1sXNOA==":"20221214-72522.jpg","kHASBe/sDNRRUNTtFyzZEg==":"20221214-72522.jpeg","zcqDccpC71eDezTUteZ70Q==":"20221214-72622.jpg","/ODI7mfZmlKuj/+2sj1lZQ==":"20221214-72622.jpeg","hyKbQG/Y+omXcl8WziaU1w==":"20221214-72822.jpg","Bweya5OTRu0O2albZ1HjCA==":"20221214-72822.jpeg","fc0f7sKFoPQO+3iXhVzL7Q==":"20221214-72725.jpg","fKQEDtFdJSf7sQKLMQDA5A==":"20221214-72725.jpeg","JlGVlK64mnvCY7AwdDXz2Q==":"20221214-81629.jpg","6VpGYAvpxz6NqAwEQCiOiQ==":"20221214-81629.jpeg","+VM5xYBZS+wSAroud1vx9A==":"fb-img-1670383057555.jpeg","+KJAk3/8sR5Df4LjSBU8KQ==":"fb_img-1670382962909-1080x810.jpeg","jxJcpPG/TyPI1sJh/fMyHQ==":"fb-img-1670383246686.jpg","+1IwGYWoE6plIpy0tr/cwA==":"fb-img-1670383246686.jpeg","gY4rSruWECVtpCXswjmALw==":"fb-img-1670383246687.jpeg","Qv5EQWsu7+PHrFp0X3JJag==":"20221214-73239.jpg","fdAvbbPzn4Jrt5T645n2hg==":"20221214-73239.jpeg","dUGebEHXcABQqS5MutWmPw==":"dsc-578.jpeg","i3owzxv8MX23//aIvuSWhA==":"img-8078.jpg","5Jg/f5fx/bCUCoZ2BzaF7A==":"img-20220728-wa0008.jpg","FesfRHi3bMO1D/QSr6jZMQ==":"img-20220728-wa0008.jpeg","q42zrKx6P5RDnOOKJ+lAXw==":"img-20220728-wa0008-1.jpeg","XOOuMxBxyOd0PJkNhad0ew==":"20221214-80623.jpeg","tt7j/xbuB5CienDAQVWjgQ==":"20221214-80624.jpeg","pxEyfoC8BjFQzhjc5KG1yQ==":"20221214-80625.jpeg","rbcpOOWN9VVjV2hEG8P1aA==":"20221214-80626.jpeg","UTCKf3b+a+RljCGZhF/FdA==":"bunga.jpg","Cqpw6zqev3GVxs0t52opXA==":"ruang-kepala-dan-kantor-tk-.-dilengkapi-3-cctv.jpg","iCzsFlcrqIW9offMluIEoA==":"ada-5-ruang-kelas.-setiap-kelas-dilengkapi-rak-sepatu-dan-loket-tas.jpg","PDYKAKdW6gQvol971G/TsA==":"ada-5-ruang-kelas.-setiap-kelas-dilengkapi-rak-sepatu-dan-loket-tas.jpeg","lazgwLhHSVqF1erlKA6BoQ==":"hall-tk.jpg","FVwL8RLTb3x+XHOT9iLoHw==":"hall-tk.jpeg","K0hyvpv2HNF6x/nIti7sEg==":"hall-tk-1.jpeg","YevNtcuDd5KzEnN0sf/OLQ==":"untitled-diagram-42.jpeg","Jetzgs5MoF5iDLVCnf7ViA==":"untitled-diagram-43.jpeg","MKvyNfFPnyJZLD+s7QMvDw==":"untitled-diagram-44.jpeg","sy07jbd1xwb8rHZl9wRySQ==":"bagantk.jpeg","QHsO/whoZsuZ99SV+1cTxw==":"151330680-3858566854206677-2233799190989783698-n.jpg","pibiOlhZAQtg36G0W3cdmA==":"img-20180111-wa0011-1.jpeg","kloesAA2YNYh3GKNVIZj4A==":"img-20180111-wa0011-2.jpeg","wi0GUuAAVaMlq07gKRRK9w==":"lambang-phdi.jpg","0kJcc/JCon70w3At17oRPQ==":"pura-phdi-1.jpg","HWYeAvj4NLxXCyyn7s+47Q==":"pembinaan2.jpg","Bt1+575XNo0hKCXHG+nVwA==":"pembinaan3.jpg","H7dDYkwvPqXKqFuL9Wfg+Q==":"pembinaan4.jpg","z2BONakLE8Ti8QiUBE1ZMQ==":"pembinaan3.jpeg","dbbG3rnfqZi1XJs0TdJUMA==":"pembinaan3-1.jpeg","gQKJU+v2EAquH5ADralRMQ==":"melasti-phdi-720x405.jpg","9wWFLU0Ocb3JoEarX+R7iw==":"pembinaan3-2.jpeg","rfN4igEbCg2AopTp6dwX1A==":"pembinaan3-3.jpeg","rcoCdYrNEs0ibORpGEhQrQ==":"pembinaan3-4.jpeg","p4IB/wQvAX62QMAQ2JpYbA==":"pura-phdi-1.jpeg","A+g8CE1/MkX4K0wfzJDVmw==":"pura-phdi-2.jpeg","pR6qFW4y4IYoZtD/5PcnLQ==":"sambutan-ketua-bd.jpg","PAApIDStIY5VLWo4bET5Tw==":"kegiatan-phdi-sleman-528x960.jpeg","o3ryOy3GnYkdgneZVbgaZw==":"kegiatan-pgdi-bantul-1076x719.jpg","xZuOi5xZ+ZjCHSd8hmzveQ==":"kegiatan-kota-phdi-diy-1024x768.jpg","g2YJpXwxvVhOf8fuVCRguw==":"kegiatan-kota-phdi-gunung-k-1024x807.jpg","vRz2wHfvenSlO42eW50dXg==":"kulon-progo-phdi-1032x774.jpg","hzH60wDPE7eX1bjKtN2OXA==":"nyepi.webp","cEOz9dcokJ2E+UAwFtb0FA==":"galungan-750x500.jpg","SfrYkRYTyecXfsT5xpH78A==":"matur-piuning-feb-unwar-745928-750x480.jpg","66hoLHYyJGE/k395M5Dmdg==":"kuningan-780x450.jpg","tDs69PWCHuKTB8+RX5l6uA==":"ket-1.jpg","KOuS7ZrAlDsrvTUkshD+Cg==":"ket-2.jpg","fGIH+KGciUK2K1bv5THfZg==":"ket-3.jpg","5ps9mezMF5NLuz3RyjzOog==":"ket-4.jpg","fvGqH5lgfGZ5RCjYKghQ5A==":"struktur-organisasi-phdi.jpg"}